{"$id":"followerDatabase","type":"object","properties":{"followerRequestId":{"default":"00000000-0000-0000-0000-000000000000","format":"uuid","type":"string"},"id":{"default":"019ab226-9302-76ca-991d-96209843c4d4","format":"uuid","type":"string"},"databaseId":{"default":"00000000-0000-0000-0000-000000000000","format":"uuid","type":"string"},"lastModified":{"default":1763925463810,"type":"number"},"touched":{"default":false,"type":"boolean"},"version":{"default":0,"minimum":0,"type":"integer"}},"required":["followerRequestId","id","databaseId","lastModified","touched","version"]}